{
  "notes.list": {
    "ts": 1777264887000,
    "iso": "2026-04-27T04:41:27.000Z"
  },
  "notes.editor": {
    "ts": 1777516010000,
    "iso": "2026-04-30T02:26:50.000Z"
  },
  "notes.entries.text": {
    "ts": 1776070783000,
    "iso": "2026-04-13T08:59:43.000Z"
  },
  "notes.entries.photo": {
    "ts": 1777264887000,
    "iso": "2026-04-27T04:41:27.000Z"
  },
  "notes.entries.video": {
    "ts": 1777264887000,
    "iso": "2026-04-27T04:41:27.000Z"
  },
  "notes.entries.audio": {
    "ts": 1777264887000,
    "iso": "2026-04-27T04:41:27.000Z"
  },
  "notes.entries.date": {
    "ts": 1766904474000,
    "iso": "2025-12-28T06:47:54.000Z"
  },
  "notes.entries.geolocation": {
    "ts": 1776070783000,
    "iso": "2026-04-13T08:59:43.000Z"
  },
  "notes.entries.framework": {
    "ts": 1777264887000,
    "iso": "2026-04-27T04:41:27.000Z"
  },
  "notes.tags": {
    "ts": 1776070783000,
    "iso": "2026-04-13T08:59:43.000Z"
  },
  "notes.priority": {
    "ts": 1777264887000,
    "iso": "2026-04-27T04:41:27.000Z"
  },
  "notes.date-picker": {
    "ts": 1766904474000,
    "iso": "2025-12-28T06:47:54.000Z"
  },
  "notes.service": {
    "ts": 1775943596000,
    "iso": "2026-04-11T21:39:56.000Z"
  },
  "notes.share-intent": {
    "ts": 1777264887000,
    "iso": "2026-04-27T04:41:27.000Z"
  },
  "streamdeck.plugin-native": {
    "ts": 1777346096000,
    "iso": "2026-04-28T03:14:56.000Z"
  },
  "streamdeck.bridge-ts": {
    "ts": 1777346096000,
    "iso": "2026-04-28T03:14:56.000Z"
  },
  "streamdeck.controller": {
    "ts": 1777516010000,
    "iso": "2026-04-30T02:26:50.000Z"
  },
  "streamdeck.usb": {
    "ts": 1777276905000,
    "iso": "2026-04-27T08:01:45.000Z"
  },
  "streamdeck.reader": {
    "ts": 1777342923000,
    "iso": "2026-04-28T02:22:03.000Z"
  },
  "streamdeck.heartbeat": {
    "ts": 1777342923000,
    "iso": "2026-04-28T02:22:03.000Z"
  },
  "streamdeck.writer-queue": {
    "ts": 1777346096000,
    "iso": "2026-04-28T03:14:56.000Z"
  },
  "streamdeck.lifecycle-service": {
    "ts": 1777277489000,
    "iso": "2026-04-27T08:11:29.000Z"
  },
  "streamdeck.camera-stream": {
    "ts": 1777356344000,
    "iso": "2026-04-28T06:05:44.000Z"
  },
  "streamdeck.face-detection": {
    "ts": 1777340084000,
    "iso": "2026-04-28T01:34:44.000Z"
  },
  "streamdeck.lcd-text": {
    "ts": 1777344352000,
    "iso": "2026-04-28T02:45:52.000Z"
  },
  "streamdeck.event-log": {
    "ts": 1777275498000,
    "iso": "2026-04-27T07:38:18.000Z"
  },
  "streamdeck.options-panel": {
    "ts": 1777356344000,
    "iso": "2026-04-28T06:05:44.000Z"
  },
  "camera.viewer": {
    "ts": 1777264887000,
    "iso": "2026-04-27T04:41:27.000Z"
  },
  "camera.ocr": {
    "ts": 1775943595000,
    "iso": "2026-04-11T21:39:55.000Z"
  },
  "sync.service": {
    "ts": 1776222127000,
    "iso": "2026-04-15T03:02:07.000Z"
  },
  "sync.options": {
    "ts": 1777356344000,
    "iso": "2026-04-28T06:05:44.000Z"
  },
  "sync.migrations": {
    "ts": 1775878417000,
    "iso": "2026-04-11T03:33:37.000Z"
  },
  "sync.notifications": {
    "ts": 1776222084000,
    "iso": "2026-04-15T03:01:24.000Z"
  },
  "code.viewer": {
    "ts": 1777354122000,
    "iso": "2026-04-28T05:28:42.000Z"
  },
  "code.style": {
    "ts": 1777356344000,
    "iso": "2026-04-28T06:05:44.000Z"
  },
  "code.editable": {
    "ts": 1777261042000,
    "iso": "2026-04-27T03:37:22.000Z"
  },
  "code.git": {
    "ts": 1777260177000,
    "iso": "2026-04-27T03:22:57.000Z"
  },
  "repos.bundle-source": {
    "ts": 1777513122000,
    "iso": "2026-04-30T01:38:42.000Z"
  },
  "repos.bundle-code": {
    "ts": 1777260031000,
    "iso": "2026-04-27T03:20:31.000Z"
  },
  "repos.extractor": {
    "ts": 1777259951000,
    "iso": "2026-04-27T03:19:11.000Z"
  },
  "repos.edit": {
    "ts": 1777261242000,
    "iso": "2026-04-27T03:40:42.000Z"
  },
  "repos.fs-factory": {
    "ts": 1777260689000,
    "iso": "2026-04-27T03:31:29.000Z"
  },
  "repos.manifest": {
    "ts": 1777259638000,
    "iso": "2026-04-27T03:13:58.000Z"
  },
  "transcription.native": {
    "ts": 1776070783000,
    "iso": "2026-04-13T08:59:43.000Z"
  },
  "transcription.download": {
    "ts": 1776070783000,
    "iso": "2026-04-13T08:59:43.000Z"
  },
  "transcription.audio-converter": {
    "ts": 1775943595000,
    "iso": "2026-04-11T21:39:55.000Z"
  },
  "transcription.bridge": {
    "ts": 1776070783000,
    "iso": "2026-04-13T08:59:43.000Z"
  },
  "transcription.options": {
    "ts": 1776070783000,
    "iso": "2026-04-13T08:59:43.000Z"
  },
  "security.biometry": {
    "ts": 1775901460000,
    "iso": "2026-04-11T09:57:40.000Z"
  },
  "security.secure-storage": {
    "ts": 1777356344000,
    "iso": "2026-04-28T06:05:44.000Z"
  },
  "security.dev-mode": {
    "ts": 1777356344000,
    "iso": "2026-04-28T06:05:44.000Z"
  },
  "system.keep-awake": {
    "ts": 1777356344000,
    "iso": "2026-04-28T06:05:44.000Z"
  },
  "system.device-info": {
    "ts": 1777356344000,
    "iso": "2026-04-28T06:05:44.000Z"
  },
  "system.network-scan": {
    "ts": 1777315247000,
    "iso": "2026-04-27T18:40:47.000Z"
  },
  "system.permissions": {
    "ts": 1777356344000,
    "iso": "2026-04-28T06:05:44.000Z"
  },
  "system.resources": {
    "ts": 1776070783000,
    "iso": "2026-04-13T08:59:43.000Z"
  },
  "system.processes": {
    "ts": 1776070783000,
    "iso": "2026-04-13T08:59:43.000Z"
  },
  "deployment.service": {
    "ts": 1775901459000,
    "iso": "2026-04-11T09:57:39.000Z"
  },
  "deployment.ssh": {
    "ts": 1776222039000,
    "iso": "2026-04-15T03:00:39.000Z"
  },
  "deployment.raw-http": {
    "ts": 1776222127000,
    "iso": "2026-04-15T03:02:07.000Z"
  },
  "deployment.deploy-ui": {
    "ts": 1776070783000,
    "iso": "2026-04-13T08:59:43.000Z"
  },
  "deployment.servers": {
    "ts": 1775943595000,
    "iso": "2026-04-11T21:39:55.000Z"
  },
  "deployment.applications": {
    "ts": 1777264887000,
    "iso": "2026-04-27T04:41:27.000Z"
  },
  "data.database": {
    "ts": 1777260689000,
    "iso": "2026-04-27T03:31:29.000Z"
  },
  "data.migrations": {
    "ts": 1774400941000,
    "iso": "2026-03-25T01:09:01.000Z"
  },
  "data.inspector": {
    "ts": 1775878417000,
    "iso": "2026-04-11T03:33:37.000Z"
  },
  "data.migration-history": {
    "ts": 1777356344000,
    "iso": "2026-04-28T06:05:44.000Z"
  },
  "data.clear-cache": {
    "ts": 1777356344000,
    "iso": "2026-04-28T06:05:44.000Z"
  },
  "ui.router": {
    "ts": 1777351525000,
    "iso": "2026-04-28T04:45:25.000Z"
  },
  "ui.theme": {
    "ts": 1777356344000,
    "iso": "2026-04-28T06:05:44.000Z"
  },
  "ui.reminders": {
    "ts": 1777356344000,
    "iso": "2026-04-28T06:05:44.000Z"
  },
  "ui.shared-components": {
    "ts": 1776222127000,
    "iso": "2026-04-15T03:02:07.000Z"
  },
  "ui.owl-aot": {
    "ts": 1777519776000,
    "iso": "2026-04-30T03:29:36.000Z"
  },
  "ui.errors": {
    "ts": 1775901459000,
    "iso": "2026-04-11T09:57:39.000Z"
  },
  "meta.home": {
    "ts": 1777347350000,
    "iso": "2026-04-28T03:35:50.000Z"
  },
  "meta.changelog": {
    "ts": 1777356344000,
    "iso": "2026-04-28T06:05:44.000Z"
  },
  "meta.erplibre": {
    "ts": 1777264887000,
    "iso": "2026-04-27T04:41:27.000Z"
  },
  "meta.feature-catalog": {
    "ts": 1777516435000,
    "iso": "2026-04-30T02:33:55.000Z"
  },
  "meta.options": {
    "ts": 1777351525000,
    "iso": "2026-04-28T04:45:25.000Z"
  },
  "meta.app-bootstrap": {
    "ts": 1777310122000,
    "iso": "2026-04-27T17:15:22.000Z"
  }
}